gqltst/__init__.py
gqltst/query.py
gqltst/reslovers.py
gqltst/schema.py
gqltst/types.py
gqltst-0.0.8.dist-info/LICENSE
gqltst-0.0.8.dist-info/METADATA
gqltst-0.0.8.dist-info/WHEEL
gqltst-0.0.8.dist-info/top_level.txt
gqltst-0.0.8.dist-info/RECORD
