Metadata-Version: 2.1
Name: gqltst
Version: 0.0.8
Summary: Framework for automatic GraphQL testing. The framework takes url of your GraphQL endpoint,
Home-page: https://github.com/pyatka/gqltst
Author: Andrey Mazur
Author-email: pyatka.aag@gmail.com
License: UNKNOWN
Platform: UNKNOWN
Classifier: Programming Language :: Python :: 3
Classifier: License :: OSI Approved :: MIT License
Classifier: Operating System :: OS Independent
